fds/__init__.py
fds/cli.py
fds/logger.py
fds/run.py
fds/utils.py
fds/version.py
fds/domain/__init__.py
fds/domain/commands.py
fds/domain/constants.py
fds/services/__init__.py
fds/services/dvc_service.py
fds/services/fds_service.py
fds/services/git_service.py
fds/services/pretty_print.py
fds/services/types.py
tests/it/__init__.py
tests/it/helpers.py
tests/it/test_dvc.py
tests/it/test_fds.py
tests/it/test_git.py
tests/it/test_run.py
fastds-0.6.0.dist-info/LICENSE
fastds-0.6.0.dist-info/METADATA
fastds-0.6.0.dist-info/WHEEL
fastds-0.6.0.dist-info/entry_points.txt
fastds-0.6.0.dist-info/top_level.txt
fastds-0.6.0.dist-info/RECORD
