Metadata-Version: 2.1
Name: fastds
Version: 0.6.0
Summary: Command line wrapper for git and dvc
Home-page: https://github.com/DAGsHub/fds
Author: DAGsHub
Author-email: contact@dagshub.com
License: MIT License
Platform: UNKNOWN
Classifier: Development Status :: 4 - Beta
Classifier: License :: OSI Approved :: MIT License
Classifier: Programming Language :: Python :: 3
Classifier: Operating System :: OS Independent
Requires-Python: >=3.6
License-File: LICENSE
Requires-Dist: colorama (==0.4.4)
Requires-Dist: humanize (==3.12.0)
Requires-Dist: progress (==1.6)
Requires-Dist: validators (==0.18.2)
Requires-Dist: requests (==2.26.0)
